moons_motor/__init__.py
moons_motor/motor.py
moons_motor/observer.py
moons_motor/simulate.py
moons_motor/status.py
moons_motor/subject.py
moons_motor-1.0.0.dist-info/licenses/LICENSE
moons_motor-1.0.0.dist-info/METADATA
moons_motor-1.0.0.dist-info/WHEEL
moons_motor-1.0.0.dist-info/top_level.txt
moons_motor-1.0.0.dist-info/RECORD
