Metadata-Version: 2.4
Name: moons_motor
Version: 1.0.0
Summary: This is a python library for controlling the Moons' motor through the serial port.
Author-email: miroc <mike8503111@gmail.com>
Project-URL: Repository, https://github.com/miroc99/moons_motor.git
Classifier: Development Status :: 4 - Beta
Classifier: Intended Audience :: Developers
Classifier: Topic :: Terminals :: Serial
Classifier: License :: OSI Approved :: MIT License
Classifier: Programming Language :: Python :: 3.12
Requires-Python: >=3.12
License-File: LICENSE
Requires-Dist: pyserial
Requires-Dist: rich
Requires-Dist: python-socketio
Requires-Dist: requests
Requires-Dist: pyserial_asyncio
Dynamic: license-file
